bennie/__init__.py
bennie/core.py
bennie/detectors/__init__.py
bennie/detectors/prepositions.py
bennie-1.0.2.dist-info/METADATA
bennie-1.0.2.dist-info/WHEEL
bennie-1.0.2.dist-info/top_level.txt
bennie-1.0.2.dist-info/RECORD
