Metadata-Version: 2.4
Name: bennie
Version: 1.0.2
Summary: A Python module for detecting dangling prepositions and other grammatical constructs.
Author-email: Will Willis <will.willis@gmail.com>
Project-URL: Homepage, https://github.com/willwillis/bennie
Project-URL: Bug Tracker, https://github.com/willwillis/bennie/issues
Keywords: grammar,nlp,english,preposition,linter
Classifier: Programming Language :: Python :: 3
Classifier: License :: OSI Approved :: MIT License
Classifier: Operating System :: OS Independent
Classifier: Development Status :: 3 - Alpha
Classifier: Intended Audience :: Developers
Classifier: Intended Audience :: Education
Classifier: Topic :: Text Processing :: Linguistic
Classifier: Topic :: Software Development :: Libraries :: Python Modules
Requires-Python: >=3.10
Requires-Dist: spacy>=3.8.7
